[{"id":1,"name":"Bulbasur","type":"fuego","locations":[{"id":1,"alt":"10.54645","long":"10.45546"},{"id":2,"alt":"20.54645","long":"20.45546"},{"id":3,"alt":"30.54645","long":"30.45546"}]},{"id":2,"name":"Squirtle","type":"agua","locations":[{"id":1,"alt":"10.54645","long":"10.45546"},{"id":2,"alt":"20.54645","long":"20.45546"},{"id":3,"alt":"30.54645","long":"30.45546"}]},{"id":3,"name":"Charmander","type":"fuego","locations":[{"id":1,"alt":"10.54645","long":"10.45546"},{"id":2,"alt":"20.54645","long":"20.45546"},{"id":3,"alt":"30.54645","long":"30.45546"}]},{"id":4,"name":"pikachu","type":"electrico","locations":[{"id":1,"alt":"10.54645","long":"10.45546"},{"id":2,"alt":"20.54645","long":"20.45546"},{"id":3,"alt":"30.54645","long":"30.45546"}]},{"id":5,"name":"eevee","type":"normal","locations":[{"id":1,"alt":"10.54645","long":"10.45546"},{"id":2,"alt":"20.54645","long":"20.45546"},{"id":3,"alt":"30.54645","long":"30.45546"}]},{"id":10,"name":"mew","type":"psiquico","locations":[{"id":1,"alt":"10.54645","long":"10.45546"},{"id":2,"alt":"20.54645","long":"20.45546"},{"id":3,"alt":"30.54645","long":"30.45546"}]},{"id":7,"name":"qqqq","type":"qqqq"},{"id":8,"name":"gggg","type":"gggg"},{"id":9,"name":"jjjjj","type":"jjjjj"},{"id":10,"name":"ppp","type":"ppp"},{"id":11,"name":"ccc","type":"ccc"},{"id":12,"name":"jjjj","type":"jjjj"},{"id":13,"name":"4444","type":"4444"},{"id":14,"name":"aaaa","type":"aaaa"},{"id":15,"name":"bbbbb","type":"bbbb"},{"id":16,"name":"8888","type":"8888"}]